curve_apps/__init__.py
curve_apps/_version.py
curve_apps/contours/__init__.py
curve_apps/contours/driver.py
curve_apps/contours/options.py
curve_apps/driver.py
curve_apps/edges/__init__.py
curve_apps/edges/driver.py
curve_apps/edges/options.py
curve_apps/peak_finder/__init__.py
curve_apps/peak_finder/anomaly.py
curve_apps/peak_finder/anomaly_group.py
curve_apps/peak_finder/application.py
curve_apps/peak_finder/base_dash.py
curve_apps/peak_finder/constants.py
curve_apps/peak_finder/driver.py
curve_apps/peak_finder/images/peak_finder_app.png
curve_apps/peak_finder/layout.py
curve_apps/peak_finder/line_anomaly.py
curve_apps/peak_finder/line_data.py
curve_apps/peak_finder/line_group.py
curve_apps/peak_finder/line_position.py
curve_apps/peak_finder/params.py
curve_apps/peak_finder/peak_finder.geoh5
curve_apps/peak_finder/utils.py
curve_apps/peak_finder/window.py
curve_apps/trend_lines/__init__.py
curve_apps/trend_lines/driver.py
curve_apps/trend_lines/options.py
curve_apps/utils.py
curve_apps-assets/__init__.py
curve_apps-assets/curve_apps_demo.geoh5
curve_apps-assets/uijson/contours.ui.json
curve_apps-assets/uijson/edge_detection.ui.json
curve_apps-assets/uijson/peak_finder.ui.json
curve_apps-assets/uijson/trend_lines.ui.json
curve_apps-0.3.0.dist-info/METADATA
curve_apps-0.3.0.dist-info/WHEEL
curve_apps-0.3.0.dist-info/licenses/LICENSE
curve_apps-0.3.0.dist-info/licenses/docs/source/THIRD_PARTY_SOFTWARE.rst
curve_apps-0.3.0.dist-info/RECORD
