Metadata-Version: 2.4
Name: curve-apps
Version: 0.3.0
Summary: Auto-detection of trends and edges in geoscientific data.
License-Expression: MIT
License-File: LICENSE
License-File: docs/source/THIRD_PARTY_SOFTWARE.rst
Author: Mira Geoscience
Author-email: support@mirageoscience.com
Maintainer: Dominique Fournier
Maintainer-email: dominiquef@mirageoscience.com
Requires-Python: >=3.10,<4.0
Classifier: Development Status :: 3 - Alpha
Classifier: Intended Audience :: Science/Research
Classifier: Natural Language :: English
Classifier: Operating System :: MacOS
Classifier: Operating System :: Microsoft :: Windows
Classifier: Operating System :: POSIX
Classifier: Operating System :: Unix
Classifier: Programming Language :: Python
Classifier: Programming Language :: Python :: 3
Classifier: Programming Language :: Python :: 3.10
Classifier: Programming Language :: Python :: 3.11
Classifier: Programming Language :: Python :: 3.12
Classifier: Programming Language :: Python :: 3.13
Classifier: Programming Language :: Python :: 3.14
Classifier: Topic :: Scientific/Engineering
Classifier: Topic :: Scientific/Engineering :: Mathematics
Classifier: Topic :: Scientific/Engineering :: Physics
Provides-Extra: webview
Requires-Dist: bottle ; extra == "webview"
Requires-Dist: dash (>=3.0.4,<4.0.0)
Requires-Dist: dash-ag-grid (>=32.3.1,<33.0.0)
Requires-Dist: dash-bootstrap-components (>=2.0.3,<3.0.0)
Requires-Dist: dash-daq (==0.6.*)
Requires-Dist: dask (>=2025.3,<2025.4.dev)
Requires-Dist: geoapps-utils (>=0.6.0b2,<0.7.dev0)
Requires-Dist: geoh5py (>=0.12.0b5,<0.13.dev0)
Requires-Dist: numpy (>=1.26.0,<1.27.0)
Requires-Dist: proxy-tools ; extra == "webview"
Requires-Dist: pydantic (>=2.5.2,<3.0.0)
Requires-Dist: pythonnet ; extra == "webview"
Requires-Dist: pywebview (>=6.0,<7.0) ; extra == "webview"
Requires-Dist: scikit-image (>=0.25.2,<0.26.0)
Requires-Dist: scipy (>=1.14.0,<1.15.0)
Requires-Dist: tqdm (>=4.66.1,<5.0.0)
Requires-Dist: waitress (>=3.0.2,<4.0.0)
Project-URL: Documentation, https://mirageoscience-curve-apps.readthedocs-hosted.com/
Project-URL: Homepage, https://www.mirageoscience.com/mining-industry-software/python-integration/
Project-URL: Repository, https://github.com/MiraGeoscience/curve-apps
